{
  "id": 809,
  "name": "에페스 필스너 330ml 24병",
  "thumbnail_image": "https://d1e2y5wc27crnp.cloudfront.net/media/smartorder_reservation/product/thumbnail/9e05ba13-6ab4-4ab3-a30e-125cfb13a8be.jpg",
  "is_hidden": false,
  "web_url": "https://api.dailyshot.co/pickup/products/809/detail/?native=true",
  "sell_type": 0,
  "en_name": "EFES Pilsner 330ml 24 bottle",
  "price": 44880,
  "discount_percent": 20,
  "is_temp_hidden": true,
  "is_hidden_at_bar": false,
  "is_temp_hidden_at_bar": true,
  "is_one_day_delivery": true,
  "pay_button_text": "모든 매장에서 품절되었습니다.",
  "pay_button_help_text": null,
  "image": null,
  "review_rate": 5,
  "review_count": 3,
  "tags": [],
  "status": 0,
  "expect_delivery_date": null,
  "expect_delivery_datetime_detail": null,
  "delivery_notice": "픽업 매장 선택 시 도착 예정일이 표시됩니다."
}